payagency_api/__init__.py
payagency_api/client.py
payagency_api/exceptions.py
payagency_api/utils.py
payagency_api/modules/__init__.py
payagency_api/modules/crypto.py
payagency_api/modules/payment.py
payagency_api/modules/payment_link.py
payagency_api/modules/payout.py
payagency_api/modules/refund.py
payagency_api/modules/transaction.py
payagency_api/types/__init__.py
payagency_api/types/common.py
payagency_api/types/crypto.py
payagency_api/types/payment.py
payagency_api/types/payment_link.py
payagency_api/types/payout.py
payagency_api/types/refund.py
payagency_api/types/transaction.py
payagency_api-1.1.0.dist-info/licenses/LICENSE
payagency_api-1.1.0.dist-info/METADATA
payagency_api-1.1.0.dist-info/WHEEL
payagency_api-1.1.0.dist-info/top_level.txt
payagency_api-1.1.0.dist-info/RECORD
