Metadata-Version: 2.4
Name: payagency-api
Version: 1.1.0
Summary: A comprehensive Python SDK for PayAgency payment processing platform
Home-page: https://github.com/vp-payomatix/payagency-python
Author: PaneruVipin
Author-email: PaneruVipin <support@pay.agency>
License-Expression: MIT
Project-URL: Homepage, https://github.com/vp-payomatix/payagency-python
Project-URL: Documentation, https://docs.pay.agency
Project-URL: Repository, https://github.com/vp-payomatix/payagency-python.git
Project-URL: Bug Tracker, https://github.com/vp-payomatix/payagency-python/issues
Keywords: payagency,payment,api,sdk,cryptocurrency,payout,card
Classifier: Programming Language :: Python :: 3
Classifier: Operating System :: OS Independent
Classifier: Development Status :: 4 - Beta
Classifier: Intended Audience :: Developers
Classifier: Topic :: Software Development :: Libraries :: Python Modules
Classifier: Topic :: Internet :: WWW/HTTP
Classifier: Topic :: Office/Business :: Financial
Requires-Python: >=3.7
License-File: LICENSE
Requires-Dist: requests>=2.25.0
Requires-Dist: cryptography>=3.4.0
Requires-Dist: typing-extensions>=4.0.0
Provides-Extra: dev
Requires-Dist: pytest>=6.0; extra == "dev"
Requires-Dist: pytest-cov>=2.10; extra == "dev"
Requires-Dist: black>=21.0; extra == "dev"
Requires-Dist: flake8>=3.8; extra == "dev"
Requires-Dist: mypy>=0.812; extra == "dev"
Dynamic: author
Dynamic: home-page
Dynamic: license-file
Dynamic: requires-python
